spyderwebb/__init__.py
spyderwebb/analyze.py
spyderwebb/extinction.py
spyderwebb/extract.py
spyderwebb/ferre.py
spyderwebb/fluxing.py
spyderwebb/photter.py
spyderwebb/qa.py
spyderwebb/reduce.py
spyderwebb/simulate.py
spyderwebb/sincint.py
spyderwebb/utils.py
spyderwebb/data/apogeedr17_rgb_feh_ann.npz
spyderwebb/data/apogeedr17_rgb_logg_ann.npz
spyderwebb/data/extinctions.txt
spyderwebb-1.0.5.data/scripts/spyderwebb
spyderwebb-1.0.5.dist-info/LICENSE
spyderwebb-1.0.5.dist-info/METADATA
spyderwebb-1.0.5.dist-info/WHEEL
spyderwebb-1.0.5.dist-info/top_level.txt
spyderwebb-1.0.5.dist-info/RECORD
